datasette_graphql/__init__.py
datasette_graphql/hookspecs.py
datasette_graphql/utils.py
datasette_graphql/static/graphiql.1.5.1.min.css
datasette_graphql/static/graphiql.1.5.1.min.js
datasette_graphql/static/react-dom.production.17.0.2.min.js
datasette_graphql/static/react.production.17.0.2.min.js
datasette_graphql/templates/graphiql.html
datasette_graphql-2.2.dist-info/METADATA
datasette_graphql-2.2.dist-info/WHEEL
datasette_graphql-2.2.dist-info/entry_points.txt
datasette_graphql-2.2.dist-info/top_level.txt
datasette_graphql-2.2.dist-info/RECORD
