Metadata-Version: 2.1
Name: datasette-graphql
Version: 2.2
Summary: Datasette plugin providing an automatic GraphQL API for your SQLite databases
Home-page: https://github.com/simonw/datasette-graphql
Author: Simon Willison
License: Apache License, Version 2.0
Project-URL: Issues, https://github.com/simonw/datasette-graphql/issues
Project-URL: CI, https://github.com/simonw/datasette-graphql/actions
Project-URL: Changelog, https://github.com/simonw/datasette-graphql/releases
Provides-Extra: test
